Metadata-Version: 1.1
Name: galgo
Version: 0.0.6.157
Summary: A collection of algorithms and tools for genome analysis
Home-page: https://github.com/m1m0r1/galgo
Author: Takahiro Mimori
Author-email: takahiro.mimori@gmail.com
License: UNKNOWN
Keywords: genome bio-informatics fasta
Platform: UNKNOWN
Classifier: Programming Language :: Python
Classifier: Topic :: Scientific/Engineering :: Bio-Informatics
